{"header":"PROCESSED on Sat, 01 Jul 2023 09:23:40 +0000 from https:\/\/shop.solarhype.at\/produkt\/wechselrichter-huawei-sun2000-10ktl-m1-hc\/","files":{"woocommerce_stripe":{"url":"\/wp-content\/plugins\/woocommerce-gateway-stripe\/assets\/js\/stripe.min.js","success":true},"jetpack-lazy-images-polyfill-intersectionobserver":{"url":"\/wp-content\/plugins\/jetpack\/jetpack_vendor\/automattic\/jetpack-lazy-images\/dist\/intersection-observer.js?minify=false","success":true},"jetpack-lazy-images":{"url":"\/wp-content\/plugins\/jetpack\/jetpack_vendor\/automattic\/jetpack-lazy-images\/dist\/lazy-images.js?minify=false","success":true}}}