{"header":"PROCESSED on Fri, 30 Jun 2023 06:43:32 +0000 from https:\/\/shop.solarhype.at\/wp-content\/uploads\/2020\/07\/Dog-hoodieDog-HoodieDog-Hoodie-600x600.jpg","files":{"cmplz-cookiebanner":{"url":"\/wp-content\/plugins\/complianz-gdpr\/cookiebanner\/js\/complianz.min.js","success":true},"smartmenus":{"url":"\/wp-content\/plugins\/elementor-pro\/assets\/lib\/smartmenus\/jquery.smartmenus.min.js","success":true},"elementor-pro-webpack-runtime":{"url":"\/wp-content\/plugins\/elementor-pro\/assets\/js\/webpack-pro.runtime.min.js","success":true},"elementor-webpack-runtime":{"url":"\/wp-content\/plugins\/elementor\/assets\/js\/webpack.runtime.min.js","success":true},"elementor-frontend-modules":{"url":"\/wp-content\/plugins\/elementor\/assets\/js\/frontend-modules.min.js","success":true}}}